selenium_compounds/__init__.py
selenium_compounds/__main__.py
selenium_compounds/decorators.py
selenium_compounds/helpers.py
selenium_compounds/config/__init__.py
selenium_compounds/config/gen_config.json
selenium_compounds/config/getter.py
selenium_compounds/config/lambdaconfig.json
selenium_compounds/page_utils/__init__.py
selenium_compounds/page_utils/confirmers.py
selenium_compounds/page_utils/getters.py
selenium_compounds/page_utils/selectors.py
selenium_compounds/page_utils/switch_window.py
selenium_compounds/webdrivers/__init__.py
selenium_compounds/webdrivers/chrome.py
selenium_compounds-1.0.0.dist-info/LICENSE
selenium_compounds-1.0.0.dist-info/METADATA
selenium_compounds-1.0.0.dist-info/WHEEL
selenium_compounds-1.0.0.dist-info/entry_points.txt
selenium_compounds-1.0.0.dist-info/top_level.txt
selenium_compounds-1.0.0.dist-info/RECORD
