Metadata-Version: 2.1
Name: selenium-compounds
Version: 1.0.0
Summary: Making selenium life easy
Author-email: Selenium Compounds <deb.moreno@pm.me>
License: The MIT License (MIT)
Project-URL: Homepage, https://google.com
Keywords: feed,reader,tutorial
Classifier: License :: OSI Approved :: MIT License
Classifier: Programming Language :: Python
Classifier: Programming Language :: Python :: 3
Requires-Python: >=3.9
License-File: LICENSE
Requires-Dist: selenium (>=4.5.0)
